Workbook

Sheet Guías
A1: Instrucciones
A2: Si hay más de un anotador, utilizar colores para distinguirlos. Cada color debe corresponder a un anotador, en lo posible debe asegurarse que la distribución sea uniforme en número
A3: En los títulos (columnas de la primera fila) pintados en amarillo están las preguntas y respuestas originales en (español, originales). La celda puede estar vacía.
A4: En los títulos (columnas de la primera fila) pintados en verde están las preguntas y respuestas a traducir al guaraní (tiene sufijo _gn y están en blanco). Si la celda amarilla anteror está en blanco, no hacer nada.
A5: En la columna de título pintada en naranja (columna 'answer'), viene la opción correcta a la pregunta (solamente como referencia)
A7: Caracteres especiales
A8: Usar cuando sea necesario los siguientes caracteres especiales:
A9: Mayúsculas | B9: Ã | C9: Ẽ | D9: G̃ | E9: Ĩ | F9: Ñ | G9: Õ | H9: Ũ | I9: Ỹ | J9: puso '
A10: Minúsculas | B10: ã | C10: ẽ | D10: g̃ | E10: ĩ | F10: ñ | G10: õ | H10: ũ | I10: ỹ | J10: puso '
A12: Cuestiones
A13: Traducir los valores de la columna amarilla (español) a la verde (guaraní)
A14: La traducción debe ser exhaustiva, excepto para nombres propios, tecnicismos, extranjerismos, nomenclaturas, signos matemáticos, etc. dentro de los textos
A15: Es posible que en las opciones de respuesta vengan únicamente números, en ese caso no hace falta traducirlos, pero sí las medidas métricas que los acompañen (siempre que sea posible)
A17: Herramientas de ayuda
A18: Se permite el uso de herramientas siempre y cuando se revisen las salidas de éstas y no sean meramente 'copia y pega' del contenido generado (es necesario revisar minuciosamente la salida del modelo).
A19: Es válido el uso de los diccionarios como apoyo, ya sean online o impresos.
A20: https://spl.gov.py/es/diccionario-guarani-paraguayo/ | B20: https://glosbe.com/es/gn | C20: https://gn.wiktionary.org/wiki/Ape | D20: https://guaraniayvu.org/ | E20: https://www.iguarani.com/
A21: Es válido el uso de traductores automáticos en línea con reconocido prestigio (como Google Translate).
A22: Google Translate | B22: AmericasNLP Helsinki
A23: Es válido el uso de IA Generativa (Modelos de lenguaje como ChatGPT, Microsoft Copilot, Gemini, Grok, etc.).
A24: https://chatgpt.com/?model=auto | B24: https://copilot.microsoft.com/ | C24: https://gemini.google.com/app | D24: https://grok.com/ | E24: https://claude.ai/login?returnTo=%2F%3F

Sheet Datos de Anotadores
D1: Hoja: test_mgsm_es_to_gn
D2: Nombre Completo | E2: E-mail | F2: Años de edad | G2: Sexo (M o F) | H2: Primera Lengua | I2: Segunda Lengua | J2: Tercera Lengua | K2: Otros datos y comentarios
A3: Anotador | B3: 1 | C3: magenta
D5: Hoja: train_mgsm_es_to_gn
D6: Nombre Completo | E6: E-mail | F6: Años de edad | G6: Sexo (M o F) | H6: Primera Lengua | I6: Segunda Lengua | J6: Tercera Lengua | K6: Otros datos y comentarios
A7: Anotador | B7: 1 | C7: magenta

Sheet test_mgsm_es_to_gn
A1: question_md5 | B1: question | C1: question_gn | D1: answer | E1: answer_gn | F1: answer_number | G1: equation_solution
A2: db8dc7716aee912fbe1c7a6cea2d8c0d | B2: Los patos de Janet ponen 16 huevos por día. Ella come tres en el desayuno todas las mañanas y usa cuatro para hornear magdalenas para sus amigos todos los días. Vende lo que sobra en el mercado de productores diariamente a $2 el huevo fresco de pato. ¿Cuánto gana en dólares todos los días en el mercado de productores? | F2: 18
A3: 04bb72b1f31714999d58a321a020306d | B3: Una bata lleva 2 rollos de tela azul y la mitad de esa cantidad de tela blanca. ¿Cuántos rollos se necesitan en total? | F3: 3
A4: d6809b5f4fd69fb26c2a96e5a1f80a85 | B4: Josh decide intentar remodelar y vender una casa. Compra una casa de $80 000 y luego agrega $50 000 para las reparaciones. Esto aumenta un 150 % el valor de la casa. ¿Cuánto obtuvo de ganancia? | F4: 70000
A5: 4378354af98e497ba0523e87a523b09d | B5: James decide correr 3 carreras de velocidad 3 veces por semana. Corre 60 metros en cada carrera de velocidad. ¿Cuántos metros corre en total por semana? | F5: 540
A6: ff78e11390b8da2f74308311d65f3739 | B6: Todos los días, Wendi alimenta a cada uno de sus pollos con tres tazas de alimento mixto para pollo que contiene semillas, larvas y verduras para ayudarlos a mantenerse saludables. Alimenta a los pollos en tres comidas separadas. Por la mañana, le da a su bandada de pollos 15 tazas de alimento. Por la tarde, le da otras 25 tazas de alimento. ¿Cuántas tazas de alimento necesita darle a sus pollos en la última comida del día si el tamaño de la bandada de Wendi es de 20 pollos? | F6: 20
A7: 9f5890f0cc71f1ffaaff76f596ce2eb2 | B7: Kylar fue a la tienda a comprar vasos para su nuevo departamento. Un vaso cuesta $5, pero cada segundo vaso cuesta solo el 60 % del precio. Kylar quiere comprar 16 vasos. ¿Cuánto dinero necesita para pagarlos? | F7: 64
A8: 56662fd702c3d077a565868f1cc86c25 | B8: En Toulouse hay el doble de ovejas que en Charleston. En Charleston hay 4 veces más ovejas que en Seattle. ¿Cuántas ovejas hay en total en Toulouse, Charleston y Seattle si en Seattle hay 20 ovejas? | F8: 260
A9: 7189c60691c05f9df90fef04cf514972 | B9: Carla está descargando un archivo de 200 GB. Por lo general, puede descargar 2 GB por minuto, pero en el 40 % de la descarga, Windows fuerza un reinicio para instalar actualizaciones, lo que demora 20 minutos. Entonces Carla tiene que reiniciar la descarga desde el principio. ¿Cuánto tiempo lleva la descarga del archivo? | F9: 160
A10: 398a850df07418abb63715ed4bf56e63 | B10: John conduce durante 3 horas a una velocidad de 60 mph y luego da la vuelta porque se da cuenta de que se olvidó algo muy importante en la casa. Intenta volver a la casa en 4 horas, pero pasa las primeras 2 horas en un embotellamiento de tráfico. La siguiente media hora conduce a una velocidad de 30 mph antes de poder conducir el tiempo restante de las 4 horas a 80 mph. ¿A qué distancia de la casa se encuentra al final de esas 4 horas? | F10: 45
A11: 00bc0d1603975674f6cd9c1e7e172df4 | B11: La tarifa de Eliza por hora para las primeras 40 horas de trabajo cada semana es $10. También recibe un pago por horas extras de 1,2 veces su tarifa habitual por hora. ¿Cuánto gana Eliza esta semana si trabajó 45 horas? | F11: 460
A12: 5ad65dc40bc15bcf364799941e54434e | B12: Un programa nuevo tuvo 60 descargas en el primer mes. La cantidad de descargas en el segundo mes fue tres veces más que las descargas en el primer mes, pero luego se redujo un 30 % en el tercer mes. ¿Cuántas descargas tuvo en total el programa durante los tres meses? | F12: 366
A13: cb6dd26d20d2b2daff398b0f789f540d | B13: Toula fue a la panadería y compró distintos tipos de pasteles. Compró 3 docenas de donas que cuestan $68 la docena, 2 docenas de mini pastelillos que cuestan $80 la docena y 6 docenas de tortitas de queso a $55 la docena. ¿Cuánto costó todo? | F13: 694
... A251: c8d5fb4ce76273f4524de486d1e766d4 | B251: El lunes, Sue comió 4 veces más de galletas que su hermana. El martes, comió dos veces más de galletas que su hermana. Su hermana comió 5 galletas el lunes y 13 al día siguiente. Si 1 galleta tiene 200 calorías, ¿cuántas calorías más consumió Sue con respecto a su hermana? | F251: 5600

Sheet train_mgsm_es_to_gn
A1: question_md5 | B1: question | C1: question_gn | D1: answer | E1: answer_gn | F1: answer_number | G1: equation_solution
A2: 2f725295caebddf465faa089251fae44 | B2: Pregunta: Roger tiene 5 pelotas de tenis. Compra 2 tubos más de pelotas de tenis. Cada tubo contiene 3 pelotas de tenis. ¿Cuántas pelotas de tenis tiene ahora? | D2: Respuesta paso a paso: Roger comenzó con 5 pelotas. 2 tubos de 3 pelotas de tenis cada uno equivale a 6 pelotas de tenis. 5 + 6 = 11. La respuesta es 11. | F2: 11 | G2: 5 + 6 = 11.
A3: 34fba4144cbcb76d860c990bf62d4e4b | B3: Pregunta: Había nueve computadoras en la sala de servidores. Se instalaron cinco computadoras cada día, de lunes a jueves. ¿Cuántas computadoras hay ahora en la sala de servidores? | D3: Respuesta paso a paso: Hay 4 días de lunes a jueves. Se agregaron 5 computadoras cada día. Eso significa que en total se agregaron 4 * 5 = 20 computadoras. Al principio, había 9 computadoras, por lo que ahora hay 9 + 20 = 29 computadoras. La respuesta es 29. | F3: 29 | G3: 4 * 5 = 20. 9 + 20 = 29.
A4: ba5aec5fbbc2e31460ef7511ac3f4cf6 | B4: Pregunta: Leah tenía 32 chocolates y su hermana tenía 42. Si se comieron 35, ¿cuántos chocolates les quedan en total? | D4: Respuesta paso a paso: Leah tenía 32 chocolates y la hermana de Leah tenía 42. Quiere decir que originalmente había 32 + 42 = 74 chocolates. Se comieron 35. Por lo tanto, en total todavía tienen 74 - 35 = 39 chocolates. La respuesta es 39. | F4: 39 | G4: 32 + 42 = 74. 74 - 35 = 39.
A5: b94a5f38a4b5d67c6fb32c0f7c6c7747 | B5: Pregunta: Shawn tiene cinco juguetes. Para Navidad, recibió dos juguetes de su mamá y dos de su papá. ¿Cuántos juguetes tiene ahora? | D5: Respuesta paso a paso: Tiene 5 juguetes. Recibió 2 de la mamá, por lo que después de eso tiene 5 + 2 = 7 juguetes. Luego, recibió 2 más del papá, así que en total tiene 7 + 2 = 9 juguetes. La respuesta es 9. | F5: 9 | G5: 5 + 2 = 7. 7 + 2 = 9.
A6: cca78ecf26e65613d7b783b9965a63bf | B6: Pregunta: Michael tenía 58 pelotas de golf. El martes, perdió 23 pelotas de golf. El miércoles, perdió 2 más. ¿Cuántas pelotas de golf tenía al final del miércoles? | D6: Respuesta paso a paso: Michael comenzó con 58 pelotas de golf y perdió 23, por lo tanto tiene 58 - 23 = 35. Después de perder 2 más, ahora tiene 35 - 2 = 33 pelotas. La respuesta es 33. | F6: 33 | G6: 58 - 23 = 35. 35 - 2 = 33.
A7: 8c48eaa022f3fe2a8d6a31330881eed0 | B7: Pregunta: Olivia tiene $23. Compró cinco roscas a $3 cada una. ¿Cuánto dinero le queda? | D7: Respuesta paso a paso: 5 roscas a $3 cada una deben costar 5 * 3 = 15 dólares. Olivia tenía $23 al principio, por lo tanto ahora le quedan 23 - 15 = 8 dólares. La respuesta es 8. | F7: 8 | G7: 5 * 3 = 15. 23 - 15 = 8.
A8: b4e68f4b38d8e14696a629ba0eca46b6 | B8: Pregunta: Jason tenía 20 chupetines. Le dio algunos chupetines a Denny. Ahora Jason tiene 12 chupetines. ¿Cuántos chupetines le dio Jason a Denny? | D8: Respuesta paso a paso: Jason comenzó con 20 chupetines, pero ahora solo tiene 12, por lo tanto le dio a Denny 20 - 12 = 8 chupetines. La respuesta es 8. | F8: 8 | G8: 20 - 12 = 8.
A9: 96a62510f8bf2889e63483ddc7c95039 | B9: Pregunta: Si hay 3 autos en el estacionamiento y llegan 2 autos más, ¿cuántos autos hay en el estacionamiento? | D9: Respuesta paso a paso: Hay 3 autos al principio, llegan 2 más, por lo tanto ahora debe haber 3 + 2 = 5 autos. La respuesta es 5. | F9: 5 | G9: 3 + 2 = 5.

Sheet Anotaciones
A1: =test_mgsm_es_to_gn!A1 -> question_md5 | B1: email | C1: traduccion
A2: =test_mgsm_es_to_gn!A2 -> db8dc7716aee912fbe1c7a6cea2d8c0d
A3: =test_mgsm_es_to_gn!A3 -> 04bb72b1f31714999d58a321a020306d
A4: =test_mgsm_es_to_gn!A4 -> d6809b5f4fd69fb26c2a96e5a1f80a85
A5: =test_mgsm_es_to_gn!A5 -> 4378354af98e497ba0523e87a523b09d
A6: =test_mgsm_es_to_gn!A6 -> ff78e11390b8da2f74308311d65f3739
A7: =test_mgsm_es_to_gn!A7 -> 9f5890f0cc71f1ffaaff76f596ce2eb2
A8: =test_mgsm_es_to_gn!A8 -> 56662fd702c3d077a565868f1cc86c25
A9: =test_mgsm_es_to_gn!A9 -> 7189c60691c05f9df90fef04cf514972
A10: =test_mgsm_es_to_gn!A10 -> 398a850df07418abb63715ed4bf56e63
A11: =test_mgsm_es_to_gn!A11 -> 00bc0d1603975674f6cd9c1e7e172df4
A12: =test_mgsm_es_to_gn!A12 -> 5ad65dc40bc15bcf364799941e54434e
A13: =test_mgsm_es_to_gn!A13 -> cb6dd26d20d2b2daff398b0f789f540d
... A259: =test_mgsm_es_to_gn!A259
